odoo10_addon_mrp_analytic-10.0.1.0.0-py2.7-nspkg.pth
odoo/addons/mrp_analytic/README.rst
odoo/addons/mrp_analytic/__init__.py
odoo/addons/mrp_analytic/__manifest__.py
odoo/addons/mrp_analytic/i18n/ca.po
odoo/addons/mrp_analytic/i18n/de.po
odoo/addons/mrp_analytic/i18n/el_GR.po
odoo/addons/mrp_analytic/i18n/es.po
odoo/addons/mrp_analytic/i18n/es_MX.po
odoo/addons/mrp_analytic/i18n/fi.po
odoo/addons/mrp_analytic/i18n/fr.po
odoo/addons/mrp_analytic/i18n/hr.po
odoo/addons/mrp_analytic/i18n/pt_BR.po
odoo/addons/mrp_analytic/i18n/sk_SK.po
odoo/addons/mrp_analytic/i18n/sl.po
odoo/addons/mrp_analytic/i18n/tr.po
odoo/addons/mrp_analytic/i18n/zh_CN.po
odoo/addons/mrp_analytic/models/__init__.py
odoo/addons/mrp_analytic/models/analytic_account.py
odoo/addons/mrp_analytic/models/mrp_production.py
odoo/addons/mrp_analytic/static/description/icon.png
odoo/addons/mrp_analytic/static/description/icon.svg
odoo/addons/mrp_analytic/tests/__init__.py
odoo/addons/mrp_analytic/tests/test_mrp_analytic.py
odoo/addons/mrp_analytic/views/analytic_account_view.xml
odoo/addons/mrp_analytic/views/mrp_view.xml
odoo10_addon_mrp_analytic-10.0.1.0.0.dist-info/DESCRIPTION.rst
odoo10_addon_mrp_analytic-10.0.1.0.0.dist-info/METADATA
odoo10_addon_mrp_analytic-10.0.1.0.0.dist-info/RECORD
odoo10_addon_mrp_analytic-10.0.1.0.0.dist-info/WHEEL
odoo10_addon_mrp_analytic-10.0.1.0.0.dist-info/metadata.json
odoo10_addon_mrp_analytic-10.0.1.0.0.dist-info/namespace_packages.txt
odoo10_addon_mrp_analytic-10.0.1.0.0.dist-info/top_level.txt
